tabpro/__init__.py
tabpro/cli.py
tabpro/commands/aggregate_tables.py
tabpro/commands/compare_tables.py
tabpro/commands/convert_tables.py
tabpro/commands/merge_tables.py
tabpro/commands/sort_tables.py
tabpro/core/actions/__init__.py
tabpro/core/actions/assign.py
tabpro/core/actions/assign_constant.py
tabpro/core/actions/assign_format.py
tabpro/core/actions/assign_id.py
tabpro/core/actions/assign_length.py
tabpro/core/actions/cast.py
tabpro/core/actions/do_action.py
tabpro/core/actions/filter_row.py
tabpro/core/actions/join_field.py
tabpro/core/actions/omit_field.py
tabpro/core/actions/parse.py
tabpro/core/actions/push_field.py
tabpro/core/actions/replace_string.py
tabpro/core/actions/setup_actions.py
tabpro/core/actions/split_field.py
tabpro/core/actions/types.py
tabpro/core/aggregate.py
tabpro/core/classes/row.py
tabpro/core/compare.py
tabpro/core/config.py
tabpro/core/console/views.py
tabpro/core/constants.py
tabpro/core/convert.py
tabpro/core/functions/as_boolean.py
tabpro/core/functions/flatten_row.py
tabpro/core/functions/get_nested_field_value.py
tabpro/core/functions/get_primary_key.py
tabpro/core/functions/nest_row.py
tabpro/core/functions/search_column_value.py
tabpro/core/functions/set_flat_field_value.py
tabpro/core/functions/set_nested_field_value.py
tabpro/core/functions/set_row_value.py
tabpro/core/io/__init__.py
tabpro/core/io/extensions/io_csv.py
tabpro/core/io/extensions/io_excel.py
tabpro/core/io/extensions/io_json.py
tabpro/core/io/extensions/io_jsonl.py
tabpro/core/io/extensions/manage_loaders.py
tabpro/core/io/extensions/manage_writers.py
tabpro/core/io/loader.py
tabpro/core/io/writer.py
tabpro/core/merge.py
tabpro/core/progress.py
tabpro/core/sort.py
tabpro/logging.py
tabpro-0.5.29.dist-info/LICENSE
tabpro-0.5.29.dist-info/METADATA
tabpro-0.5.29.dist-info/WHEEL
tabpro-0.5.29.dist-info/entry_points.txt
tabpro-0.5.29.dist-info/RECORD
